{
    "type": "minecraft:crafting_shaped",
    "pattern": [
        " # ",
        " /#",
        "/  "
    ],
    "key": {
        "#": {
            "item": "astralsorcery:marble_raw"
        },
        "/": {
            "tag": "forge:rods/wooden"
        }
    },
    "result": {
        "item": "tetra:modular_double",
        "nbt": {
            "id": "acce11a6-121d-47ba-b3ed-bfd06b31af38",
            "double/head_left": "double/basic_hammer_left",
            "double/basic_hammer_left_material": "basic_hammer/astralsorcery_marble",
            "double/head_right": "double/basic_hammer_right",
            "double/basic_hammer_right_material": "basic_hammer/astralsorcery_marble",
            "double/handle": "double/basic_handle",
            "double/basic_handle_material": "basic_handle/stick"
        }
    }
}