{
    "type": "minecraft:crafting_shaped",
    "pattern": [
        " # ",
        " /#",
        "/  "
    ],
    "key": {
        "#": {
            "item": "embellishcraft:larvikite_cobblestone"
        },
        "/": {
            "tag": "forge:rods/wooden"
        }
    },
    "result": {
        "item": "tetra:modular_double",
        "nbt": {
            "id": "82eb5431-3062-4ea4-8bb1-ddf1f8193e77",
            "double/head_left": "double/basic_hammer_left",
            "double/basic_hammer_left_material": "basic_hammer/embellishcraft_larvikite_cobblestone",
            "double/head_right": "double/basic_hammer_right",
            "double/basic_hammer_right_material": "basic_hammer/embellishcraft_larvikite_cobblestone",
            "double/handle": "double/basic_handle",
            "double/basic_handle_material": "basic_handle/stick"
        }
    }
}